yandex/Translater.py
yandex/__init__.py
yandex_translater-6.0.dist-info/LICENSE-BSD
yandex_translater-6.0.dist-info/METADATA
yandex_translater-6.0.dist-info/WHEEL
yandex_translater-6.0.dist-info/top_level.txt
yandex_translater-6.0.dist-info/RECORD
